{"metadata": {" ": "269", "file": "GerDracor/lenz-die-freunde-machen-den-philosophen.xml", "author": "Lenz, Jakob Michael Reinhold", "title": "Die Freunde machen den Philosophen", "Untertitel1": "Eine Kom\u00f6die", "Untertitel2": "Jakob Michael Reinhold Lenz: Werke und Schriften. Herausgegeben von Britta Titel\n und Hellmut Haug, Band 1\u20132, Stuttgart: Goverts, 1965\u20131966.", "genretitle": "Kom\u00f6die", "genre classification": "K", "subgenre": "", "Sortierdatum": "1776", "UAOrt": "", "UAB\u00fchne": "", "UATruppe": "", "Dramatis_Personae": "no", "act_count": "5", "scene_count": "20"}, "aggregation_data": {"emotions": [{"emotional movement": 238}, {"suffering": 133}, {"joy": 92}, {"anger": 115}, {"fear": 39}, {"compassion": 14}, {"hate, disgust": 45}, {"love": 72}, {"despair": 14}, {"friendship": 20}, {"admiration": 44}, {"Schadenfreude": 11}]}}