{"metadata": {" ": "115", "file": "GerDracor/tieck-ritter-blaubart.xml", "author": "Tieck, Ludwig", "title": "Ritter Blaubart", "Untertitel1": "Ein Ammenm\u00e4rchen in vier Akten", "Untertitel2": "Ludwig Tieck: Werke in einem Band. Mit einem Nachwort von Richard Alewyn,\n Hamburg: Hoffmann und Campe, 1967.", "genretitle": "M\u00e4rchen", "genre classification": "T", "subgenre": "", "Sortierdatum": "1797", "UAOrt": "D\u00fcsseldorf", "UAB\u00fchne": "", "UATruppe": "", "Dramatis_Personae": "no", "act_count": "4", "scene_count": "15"}, "aggregation_data": {"emotions": [{"joy": 290}, {"suffering": 287}, {"Schadenfreude": 31}, {"emotional movement": 393}, {"hate, disgust": 102}, {"anger": 315}, {"fear": 127}, {"admiration": 43}, {"friendship": 29}, {"love": 78}, {"compassion": 35}, {"despair": 13}]}}