{"metadata": {" ": "500", "file": "GerDracor/kleist-die-familie-schroffenstein.xml", "author": "Kleist, Heinrich von", "title": "Die Familie Schroffenstein", "Untertitel1": "Ein Trauerspiel in f\u00fcnf Aufz\u00fcgen", "Untertitel2": "Heinrich von Kleist: Werke und Briefe in vier B\u00e4nden. Herausgegeben von Siegfried\n Streller in Zusammenarbeit mit Peter Goldammer und Wolfgang Barthel, Anita Golz,\n Rudolf Loch, Berlin und Weimar: Aufbau, 1978.", "genretitle": "Trauerspiel", "genre classification": "T", "subgenre": "", "Sortierdatum": "1803", "UAOrt": "Graz", "UAB\u00fchne": "Nationaltheater", "UATruppe": "", "Dramatis_Personae": "no", "act_count": "5", "scene_count": "13"}, "aggregation_data": {"emotions": [{"anger": 495}, {"emotional movement": 816}, {"suffering": 384}, {"joy": 236}, {"hate, disgust": 219}, {"friendship": 42}, {"admiration": 71}, {"love": 155}, {"fear": 186}, {"despair": 50}, {"Schadenfreude": 37}, {"compassion": 68}]}}