{"metadata": {" ": "349", "file": "GerDracor/eckartshausen-der-pudelhund.xml", "author": "Eckartshausen, Karl von", "title": "Der Pudelhund", "Untertitel1": "Ein Lustspiel in einem Aufzuge", "Untertitel2": "Der Pudelhund. Ein Lustspiel in einem Aufzuge, von K. von Eckartshausen. M\u00fcnchen,\n bey Joseph Lentner. 1800.", "genretitle": "Lustspiel", "genre classification": "K", "subgenre": "", "Sortierdatum": "1800", "UAOrt": "", "UAB\u00fchne": "", "UATruppe": "", "Dramatis_Personae": "", "act_count": "", "scene_count": ""}, "aggregation_data": {"emotions": [{"emotional movement": 130}, {"anger": 87}, {"suffering": 70}, {"joy": 113}, {"love": 97}, {"hate, disgust": 42}, {"friendship": 14}, {"Schadenfreude": 16}, {"admiration": 30}, {"compassion": 23}, {"despair": 7}, {"fear": 21}]}}