{"metadata": {" ": "", "file": "kasperl_Perinet_Eifersucht.xml", "author": "", "title": "", "Untertitel1": "", "Untertitel2": "", "genretitle": "Kom\u00f6die", "genre classification": "K", "subgenre": "K", "Sortierdatum": "", "UAOrt": "", "UAB\u00fchne": "", "UATruppe": "", "Dramatis_Personae": "", "act_count": "", "scene_count": ""}, "aggregation_data": {"emotions": [{"emotional movement": 350}, {"anger": 217}, {"suffering": 182}, {"hate, disgust": 58}, {"fear": 70}, {"joy": 135}, {"love": 107}, {"Schadenfreude": 20}, {"compassion": 30}, {"admiration": 58}, {"friendship": 26}, {"despair": 12}]}}